[{
    "id": 1,
    "question": "__________ is one of the most critical functions of management that involves placing the right individuals in the right positions at the right time.",
    "answer": "Staffing"
  },
  {
    "id": 2,
    "question": "Organizations are social entities that rely heavily on __________ to fulfill their goals effectively.",
    "answer": "human resources"
  },
  {
    "id": 3,
    "question": "The complexity of organizational goals often requires multiple __________ to ensure tasks are completed efficiently.",
    "answer": "roles"
  },
  {
    "id": 4,
    "question": "Educational institutions need staffing to achieve their primary goal of __________ development of students.",
    "answer": "holistic"
  },
  {
    "id": 5,
    "question": "__________ plays a crucial role in staffing by evaluating candidates based on their skills and qualifications.",
    "answer": "Selection"
  },
  {
    "id": 6,
    "question": "An example of a staffing role in schools is the __________, who provides leadership and strategic direction.",
    "answer": "principal"
  },
  {
    "id": 7,
    "question": "Staffing includes __________ to equip employees with the necessary skills and knowledge.",
    "answer": "training and development"
  },
  {
    "id": 8,
    "question": "Without proper staffing, organizations risk __________, leading to inefficiency and failure to meet goals.",
    "answer": "operational gaps"
  },
  {
    "id": 9,
    "question": "A key part of staffing is __________, which ensures that individuals selected for roles meet the specific job requirements.",
    "answer": "performance appraisal"
  },
  {
    "id": 10,
    "question": "The process of staffing involves __________, __________, __________, and __________.",
    "answer": "recruitment, selection, placement, orientation"
  }
]
